pycin/__init__.py
pycin/pycin.py
pycin-0.1.0.dist-info/LICENSE
pycin-0.1.0.dist-info/METADATA
pycin-0.1.0.dist-info/WHEEL
pycin-0.1.0.dist-info/top_level.txt
pycin-0.1.0.dist-info/RECORD
