Metadata-Version: 2.1
Name: pycin
Version: 0.1.0
Summary: Python interface for the Hungarian Cinema City API.
Home-page: https://github.com/Mrpatekful/pycin
Author: Patrik Purgai
Author-email: purgai.patrik@gmail.com
License: UNKNOWN
Platform: UNKNOWN
Classifier: Programming Language :: Python :: 3
Classifier: License :: OSI Approved :: MIT License
Classifier: Operating System :: OS Independent
